hoop_diagram/__init__.py
hoop_diagram/visualize.py
hoop_diagram-0.0.3.dist-info/LICENSE.md
hoop_diagram-0.0.3.dist-info/METADATA
hoop_diagram-0.0.3.dist-info/WHEEL
hoop_diagram-0.0.3.dist-info/top_level.txt
hoop_diagram-0.0.3.dist-info/RECORD
