Metadata-Version: 2.1
Name: hoop-diagram
Version: 0.0.3
Summary: Visualize set intersections.
Author-email: "Yannik T. H. Schelske" <yannik@yths.de>
License: MIT License
Project-URL: Homepage, https://github.com/yths/hoop-diagram
Project-URL: Issues, https://github.com/yths/hoop-diagram/issues
Keywords: Visualization,Set,Hoop Diagram,Linear Diagram,Set Visualization,SVG
Classifier: Programming Language :: Python :: 3
Classifier: License :: OSI Approved :: MIT License
Classifier: Operating System :: OS Independent
Requires-Python: >=3.12
License-File: LICENSE.md
Requires-Dist: pycairo ==1.27.0
Requires-Dist: pillow ==11.0.0
